voltops/__init__.py
voltops/core/__init__.py
voltops/core/quantities.py
voltops/formulas/__init__.py
voltops/formulas/basic.py
voltops/image_processing/__init__.py
voltops/signal_processing/__init__.py
voltops/signal_processing/filters.py
voltops/signal_processing/transforms.py
voltops-0.2.0.dist-info/METADATA
voltops-0.2.0.dist-info/WHEEL
voltops-0.2.0.dist-info/top_level.txt
voltops-0.2.0.dist-info/RECORD
