Metadata-Version: 2.4
Name: voltops
Version: 0.2.0
Summary: A Python library for electronic formulas and signal processing
Home-page: https://github.com/madhurthareja/voltops
Author: Madhur Thareja
Author-email: madhurthareja1105@gmail.com
Classifier: Programming Language :: Python :: 3
Classifier: License :: OSI Approved :: MIT License
Classifier: Operating System :: OS Independent
Requires-Python: >=3.7
Requires-Dist: numpy>=1.21.0
Requires-Dist: scipy>=1.7.0
Dynamic: author
Dynamic: author-email
Dynamic: classifier
Dynamic: description
Dynamic: description-content-type
Dynamic: home-page
Dynamic: requires-dist
Dynamic: requires-python
Dynamic: summary
